README.rst
setup.cfg
setup.py
swagger_render/__init__.py
swagger_render/__main__.py
swagger_render/__version__.py
swagger_render/colors.py
swagger_render/filters.py
swagger_render.egg-info/PKG-INFO
swagger_render.egg-info/SOURCES.txt
swagger_render.egg-info/dependency_links.txt
swagger_render.egg-info/entry_points.txt
swagger_render.egg-info/requires.txt
swagger_render.egg-info/top_level.txt
swagger_render/templates/page.html