Metadata-Version: 1.1
Name: swagger-render
Version: 1.4.0
Summary: Renders Swagger APIs
Home-page: UNKNOWN
Author: Juhani Imberg
Author-email: juhani@imberg.com
License: UNKNOWN
Platform: UNKNOWN
Classifier: Development Status :: 3 - Alpha
Classifier: Environment :: Web Environment
Classifier: Intended Audience :: Developers
Classifier: License :: OSI Approved :: MIT License
Classifier: Topic :: Documentation
